DTALite/DTALite.py
DTALite/__init__.py
DTALite/bin/DTALite.dll
DTALite/bin/DTALite.so
DTALite/bin/DTALite_arm.dylib
DTALite/bin/DTALite_x86.dylib
dtalite-0.8.1.dist-info/METADATA
dtalite-0.8.1.dist-info/WHEEL
dtalite-0.8.1.dist-info/top_level.txt
dtalite-0.8.1.dist-info/RECORD
