Metadata-Version: 2.4
Name: DTALite
Version: 0.8.1
Summary: An open-source, cross-platform, lightweight, and fast Python                Dynamic Traffic Assignment engine for networks encoded in GMNS
Home-page: https://github.com/itsfangtang/DTALite_release
Author: Fang Tang, Dr. Xuesong Zhou
Author-email: fangt@asu.edu, xzhou74@asu.edu
License: Apache License 2.0
Classifier: Programming Language :: Python :: 3
Classifier: License :: OSI Approved :: Apache Software License
Classifier: Operating System :: OS Independent
Dynamic: author
Dynamic: author-email
Dynamic: classifier
Dynamic: description
Dynamic: description-content-type
Dynamic: home-page
Dynamic: license
Dynamic: summary
